fast_dist.cpython-311-darwin.so
fast_score.cpython-311-darwin.so
ChromoPhyloGen/ChromoPhyloGen.py
ChromoPhyloGen/__init__.py
ChromoPhyloGen/__main__.py
ChromoPhyloGen/cli_main.py
ChromoPhyloGen/distance.py
ChromoPhyloGen/estimateDER.py
ChromoPhyloGen/events_define.py
ChromoPhyloGen/huffmanTree.py
ChromoPhyloGen/infer_tree.py
ChromoPhyloGen/keyCNA.py
ChromoPhyloGen/tree_class.py
ChromoPhyloGen/utils.py
ChromoPhyloGen/data/cancer_ploity_gmm_param.txt
ChromoPhyloGen/data/exampleCNA.txt
ChromoPhyloGen/data/exampleCNA1.txt
ChromoPhyloGen/data/exampleCNA2.txt
ChromoPhyloGen-1.0.dist-info/LICENSE
ChromoPhyloGen-1.0.dist-info/METADATA
ChromoPhyloGen-1.0.dist-info/WHEEL
ChromoPhyloGen-1.0.dist-info/entry_points.txt
ChromoPhyloGen-1.0.dist-info/top_level.txt
ChromoPhyloGen-1.0.dist-info/RECORD
