Metadata-Version: 2.1
Name: ChromoPhyloGen
Version: 1.0
Summary: A package for inferring CNA fitness evolutionary trees and CNAs' evolutionary efficiency.
Home-page: https://github.com/FangWang-SYSU/ChromoPhyloGen.git
Author: XinWang
Author-email: wangx768@mail2.sysu.edu.cn
License: MIT
Keywords: Single cell,phylogenetic tree,CNA,evolutionary efficiency
Classifier: Programming Language :: Python :: 3
Classifier: License :: OSI Approved :: MIT License
Classifier: Operating System :: OS Independent
Requires-Python: >=3.9
License-File: LICENSE
Requires-Dist: biopython
Requires-Dist: Cython
Requires-Dist: numpy
Requires-Dist: pandas
Requires-Dist: scikit-learn
Requires-Dist: scipy
Requires-Dist: tqdm
Requires-Dist: snfpy
Requires-Dist: matplotlib
Requires-Dist: seaborn
Requires-Dist: statsmodels
